.keep
marrow/interface/__init__.py
marrow/interface/meta.py
marrow/interface/release.py
marrow/interface/schema.py
marrow/interface/__pycache__/__init__.cpython-37.opt-1.pyc
marrow/interface/__pycache__/meta.cpython-37.opt-1.pyc
marrow/interface/__pycache__/release.cpython-37.opt-1.pyc
marrow/interface/__pycache__/schema.cpython-37.opt-1.pyc
marrow.interface-2.0.0.dist-info/LICENSE.txt
marrow.interface-2.0.0.dist-info/METADATA
marrow.interface-2.0.0.dist-info/WHEEL
marrow.interface-2.0.0.dist-info/top_level.txt
marrow.interface-2.0.0.dist-info/RECORD
