Metadata-Version: 2.1
Name: marrow.interface
Version: 2.0.0
Summary: An anti-Pythonic declarative strict interface definition and validation system.
Home-page: https://github.com/marrow/interface/
Author: Alice Bevan-McGregor
Author-email: alice@gothcandy.com
License: MIT
Keywords: interface enforcement
Platform: UNKNOWN
Classifier: Development Status :: 5 - Production/Stable
Classifier: Environment :: Console
Classifier: Intended Audience :: Developers
Classifier: License :: OSI Approved :: MIT License
Classifier: Operating System :: OS Independent
Classifier: Programming Language :: Python
Classifier: Programming Language :: Python :: 3
Classifier: Programming Language :: Python :: 3.3
Classifier: Programming Language :: Python :: 3.4
Classifier: Programming Language :: Python :: 3.5
Classifier: Programming Language :: Python :: 3.6
Classifier: Programming Language :: Python :: 3.7
Classifier: Programming Language :: Python :: Implementation :: CPython
Classifier: Programming Language :: Python :: Implementation :: PyPy
Classifier: Topic :: Software Development :: Libraries :: Python Modules
Requires-Dist: marrow.schema (>=2.0)
Provides-Extra: development
Requires-Dist: pytest ; extra == 'development'
Requires-Dist: pytest-cov ; extra == 'development'
Requires-Dist: pytest-flakes ; extra == 'development'
Requires-Dist: pytest-isort ; extra == 'development'
